{
 "name": "Review: AEROMEXICO's 787 BUSINESS CLASS - How good is it?",
 "description": "▶︎ Support ME and become a PATRON for many more perks! \n\nhttps://www.patreon.com/joshcahill\n\nThis is a comprehensive Flight Review of AeroMexico.\n\nClass: Business\nRoute: London (LHR) to Mexico City (MEX)\nPlane: B787-8\n\n▶︎ Follow me on Instagram, Facebook, TikTok and Twitter!\n\nhttps://instagram.com/gotravelyourway\nhttps://www.facebook.com/gotravelyourway\nhttps://twitter.com/gotravelyourway\nhttps://www.tiktok.com/@gotravelyourway\n\n▶︎ My Website: http://www.gotravelyourway.com\n▶︎ Email Contact: gotravelyourway@gmail.com\n\nMusic:\n\nSpite by ZAYFALL https://soundcloud.com/zayfallmusic\nCreative Commons — Attribution 3.0 Unported  — CC BY 3.0 \nhttp://creativecommons.org/licenses/b...\nMusic promoted by Audio Library https://youtu.be/PLw9glZjEbQ\n\n#aeromexico #joshcahill #mexico",
 "source": "youtube",
 "source_id": "IUz8jJmZhmk",
 "type": "Flight",
 "company": "",
 "stops": [],
 "postdate": "2019-05-24T05:00:05Z"
}