{
 "name": "BUSINESS CLASS from BALI to JAKARTA | Trip Report",
 "description": "EDIT: I flew into the new Terminal 3 at Jakarta, not Terminal 1!\n\nJoin me on the first leg of my journey from Bali to Washington, DC, USA. I took the long way back, traveling via Abu Dhabi. The first part of my trip took me from Denpasar in Bali to Jakarta with Garuda Indonesia's Business Class!\n\nCheck out my experience flying FIRST CLASS with Garuda: https://www.youtube.com/watch?v=sF9KHRDBju8&t=328s\n\nAlso, here's a link to the Inauguaral Flight of Delta's A350:\nhttps://www.youtube.com/watch?v=aFUGR0-7XWc&t=152s\n\n\nPlease \"Like,\" \"Comment,\" and \"Subscribe!\"\n\nCheck out my travel blog: https://greenergrass.com/\n\nInstagram: https://www.instagram.com/jebbrooks/\n\nMusic is \"A Place Of Wonder And Beauty\" by Johannes Bornlöf",
 "source": "youtube",
 "source_id": "07MMPzGudHs",
 "type": "Flight",
 "company": "",
 "stops": [],
 "postdate": "2017-11-14T14:15:34Z"
}