{
 "name": "Boeing 747-400LCF \"Dreamlifter\" Departing Paine Field",
 "description": "No description available.\n\n\nOkay, you want a description? Here's one.\n\nMY AUTO-FOCUS SUCKS!\n\n_____________________________________________________\n\nFLIGHT INFO\nFlightAware: www.flightaware.com/live/flight/N249BA\nAircraft registration: N249BA\nCallsign: Giant ???? Heavy\nRunway used: 16R\n_____________________________________________________\n\n© dude8472productions 2013\n\nThis video is the property of dude8472productions and may not be used in any way without permission.",
 "source": "youtube",
 "source_id": "bdazOYPBzJE",
 "type": "Flight",
 "company": "",
 "stops": [],
 "postdate": "2013-08-15T18:03:11Z"
}