{
 "name": "EUROPE'S BEST SHORTHAUL BUSINESS CLASS? Turkish Airlines Airbus A330-300 Review",
 "description": "I flew Business Class on Turkish Airlines' wonderful Airbus A330-300 service from London to Istanbul, and sampled the Singapore Airlines SilverKris Loungenat London Heathrow.\n\n=====\nEARLY ACCESS, FULL LENGTH FLIGHTS, MERCH & MORE: SUPPORT ME ON PATREON: http://www.patreon.com/inflightvideo\n\nCHECK OUT PRIORITY PASS FOR LOUNGE ACCESS - 10% DISCOUNT FOR MY VIEWERS: https://bit.ly/2BGDwOo (affiliate link)\n\nPLEASE SUBSCRIBE FOR WEEKLY TRIP REPORTS!\n\nEQUIPMENT (affiliate links)\nGoPro Hero 7 https://amzn.to/2SVH1er\nFeiyutech G6 Gimbal https://amzn.to/2NsNXd7\nZoom H1N Voice Recorder: https://amzn.to/2NmXu5d\nEdutige ETM-001 Lav Mic: https://amzn.to/2E92wxU\n\n=====\n\nAirline: Turkish Airlines\nFlight: TK1986\nAircraft: Airbus A330-300 TC-JOM\nFrom: London (LHR)\nTo: Istanbul (IST)\nDeparture: 16:22\nArrival: 22:44\nFlight Time: 4:22\nSeat: 4K",
 "source": "youtube",
 "source_id": "R-SDRdeYA4I",
 "type": "Flight",
 "company": "",
 "stops": [],
 "postdate": "2019-01-25T13:59:59Z"
}