{
 "name": "Flying the TEQUILA EXPRESS! AeroMexico 787 Business Class",
 "description": "What's it like flying AeroMexico's Boeing 787 Business Class? I took a ride with them to find out.\n\nOFFICIAL NOEL MERCH: www.noelphilips.com\nMY CAMERA: https://amzn.to/3q6qRf8\nJOIN ME ON WHATSAPP, GET WEEKLY LIVE CHATS AND MUCH MORE - SUPPORT ME ON PATREON! http://patreon.com/inflightvideo\n(affiliate links)\n\nTHANK YOU TO MY AWESOME PATRONS!  Join them at patreon.com/inflightvideo",
 "source": "youtube",
 "source_id": "e57tLHkPVrs",
 "type": "Flight",
 "company": "",
 "stops": [],
 "postdate": "2021-02-14T12:59:55Z"
}