{
 "name": "I Took America's LONGEST Sleeper Train: 3 Days!",
 "description": "This week I take a ride on America's longest train ride - the Amtrak California Zephyr from Chicago to San Francisco in First Class in their Bedroom Suite.\n\nOFFICIAL NOEL MERCH: https://www.noelphilips.com\nMY PILOT VLOGS CHANNEL:  @NoelPhilipsPilotVlogs\nJOIN ME ON WHATSAPP, GET WEEKLY LIVE CHATS AND MUCH MORE - SUPPORT ME ON PATREON! http://patreon.com/inflightvideo",
 "source": "youtube",
 "source_id": "bpV7Kc7U2Qw",
 "type": "Flight",
 "company": "",
 "stops": [],
 "postdate": "2023-12-24T14:00:01Z"
}