{
 "name": "Caledonian Sleeper, First Class, London to Inverness",
 "description": "Check out my Europe by Train Bright Trip guide: https://www.brighttrip.com/europebytrain\nWATCH: AZUMA: Britain’s NEW high speed train: https://youtu.be/Y8ti6V73F0c\n\nFancy being a Patron? https://www.patreon.com/paulstripreports\n\nFollow me on Snapchat: pauls_trips ¦ https://snapchat.com/add/pauls_trips\n\nFollow me on Twitter: @pauls_trips ¦ https://twitter.com/pauls_trips\n\nFollow me on Instagram: paulstripreports ¦ https://www.instagram.com/paulstripre...\n\nDate of Travel: 01 FEB 2017\nTOC: Caledonian Sleeper\nConsist: Class 90/Class 67 locomotive + 16 MkII/MkIII carriages\nLivery: Old CS livery\nRoute: EUS-INV\nTravel Time: 13h03m\nMiles: 567\nRemarks: None\n\n\nThanks for finding my video and pressing play! \n\nJoin me as I take the Caledonian Sleeper - one of Britain's oldest trains - between London Euston and Inverness in the Scottish Highlands. Featuring a detailed walkaround of the sleeper berth, lounge car, dinner, breakfast and all the quirks of the journey in between.\n\nEverything you need to know about the present sleeper, its past, and the exciting plans for the future is here: https://en.wikipedia.org/wiki/Caledonian_Sleeper\n\nMY MOST-WATCHED VIDEO - BRITISH AIRWAYS FIRST CLASS 787 REPORT: https://www.youtube.com/watch?v=4LRFy... \n\nANOTHER TRAIN TRIP: https://www.youtube.com/watch?v=FYyRAdfHalc&list=PL-NSRmEdAZbOChpKx89tgNbYlQCsBrOns&index=2\n\n\n#paulstripreports #vlog #review #trains #travel #aviation #avgeek #railfan\n\nMusic: Audionautix - Sailor's Lament\n\n***DON’T FORGET TO SUBSCRIBE!***",
 "source": "youtube",
 "source_id": "YKQgkqdIhDc",
 "type": "Flight",
 "company": "",
 "stops": [],
 "postdate": "2017-02-12T15:24:04Z"
}